git/__init__.py
git/cmd.py
git/compat.py
git/config.py
git/db.py
git/diff.py
git/exc.py
git/py.typed
git/remote.py
git/types.py
git/util.py
git/index/__init__.py
git/index/base.py
git/index/fun.py
git/index/typ.py
git/index/util.py
git/objects/__init__.py
git/objects/base.py
git/objects/blob.py
git/objects/commit.py
git/objects/fun.py
git/objects/tag.py
git/objects/tree.py
git/objects/util.py
git/objects/submodule/__init__.py
git/objects/submodule/base.py
git/objects/submodule/root.py
git/objects/submodule/util.py
git/refs/__init__.py
git/refs/head.py
git/refs/log.py
git/refs/reference.py
git/refs/remote.py
git/refs/symbolic.py
git/refs/tag.py
git/repo/__init__.py
git/repo/base.py
git/repo/fun.py
GitPython-3.1.42.dist-info/AUTHORS
GitPython-3.1.42.dist-info/LICENSE
GitPython-3.1.42.dist-info/METADATA
GitPython-3.1.42.dist-info/WHEEL
GitPython-3.1.42.dist-info/top_level.txt
GitPython-3.1.42.dist-info/RECORD
