Metadata-Version: 2.1
Name: GitPython
Version: 3.1.42
Summary: GitPython is a Python library used to interact with Git repositories
Home-page: https://github.com/gitpython-developers/GitPython
Author: Sebastian Thiel, Michael Trier
Author-email: byronimo@gmail.com, mtrier@gmail.com
License: BSD-3-Clause
Classifier: Development Status :: 5 - Production/Stable
Classifier: Environment :: Console
Classifier: Intended Audience :: Developers
Classifier: License :: OSI Approved :: BSD License
Classifier: Operating System :: OS Independent
Classifier: Operating System :: POSIX
Classifier: Operating System :: Microsoft :: Windows
Classifier: Operating System :: MacOS :: MacOS X
Classifier: Typing :: Typed
Classifier: Programming Language :: Python
Classifier: Programming Language :: Python :: 3
Classifier: Programming Language :: Python :: 3.7
Classifier: Programming Language :: Python :: 3.8
Classifier: Programming Language :: Python :: 3.9
Classifier: Programming Language :: Python :: 3.10
Classifier: Programming Language :: Python :: 3.11
Classifier: Programming Language :: Python :: 3.12
Requires-Python: >=3.7
License-File: LICENSE
License-File: AUTHORS
Requires-Dist: gitdb<5,>=4.0.1
Requires-Dist: typing-extensions>=3.7.4.3; python_version < "3.8"
Provides-Extra: test
Requires-Dist: black; extra == "test"
Requires-Dist: coverage[toml]; extra == "test"
Requires-Dist: ddt!=1.4.3,>=1.1.1; extra == "test"
Requires-Dist: mock; python_version < "3.8" and extra == "test"
Requires-Dist: mypy; extra == "test"
Requires-Dist: pre-commit; extra == "test"
Requires-Dist: pytest>=7.3.1; extra == "test"
Requires-Dist: pytest-cov; extra == "test"
Requires-Dist: pytest-instafail; extra == "test"
Requires-Dist: pytest-mock; extra == "test"
Requires-Dist: pytest-sugar; extra == "test"
